hissdb/__init__.py
hissdb/column.py
hissdb/db.py
hissdb/expression.py
hissdb/functions.py
hissdb/statements.py
hissdb/table.py
hissdb-0.0.5.dist-info/LICENSE
hissdb-0.0.5.dist-info/METADATA
hissdb-0.0.5.dist-info/WHEEL
hissdb-0.0.5.dist-info/top_level.txt
hissdb-0.0.5.dist-info/RECORD
