Metadata-Version: 2.1
Name: hissdb
Version: 0.0.5
Summary: a simple SQLite query builder with a few bells and whistles
Home-page: https://github.com/raindrum/hissdb
Author: Simon Raindrum Sherred
Author-email: simonraindrum@gmail.com
License: None
Classifier: Programming Language :: Python :: 3.9
Classifier: Operating System :: OS Independent
Classifier: Topic :: Software Development :: Libraries :: Python Modules
Classifier: Topic :: Database :: Front-Ends
License-File: LICENSE
